python_flutterwave/__init__.py
python_flutterwave/decorators.py
python_flutterwave/exceptions.py
python_flutterwave/objects.py
python_flutterwave/charge/__init__.py
python_flutterwave/charge/bank.py
python_flutterwave/charge/card.py
python_flutterwave/charge/mobile.py
python_flutterwave/charge/validation.py
python_flutterwave/tokenization/__init__.py
python_flutterwave/tokenization/tokenized_charge.py
python_flutterwave-1.2.1.dist-info/LICENSE
python_flutterwave-1.2.1.dist-info/METADATA
python_flutterwave-1.2.1.dist-info/WHEEL
python_flutterwave-1.2.1.dist-info/top_level.txt
python_flutterwave-1.2.1.dist-info/RECORD
