Metadata-Version: 2.1
Name: python-flutterwave
Version: 1.2.1
Summary: Python Wrapper for interacting with the Flutterwave Payments API
Home-page: https://github.com/WilliamOtieno/python-flutterwave
Author: William Otieno
Author-email: jimmywilliamotieno@gmail.com
Classifier: Programming Language :: Python :: 3
Classifier: License :: OSI Approved :: MIT License
Classifier: Operating System :: OS Independent
Requires-Python: >=3.8
License-File: LICENSE
Requires-Dist: requests
